ultrayolo/__init__.py
ultrayolo/cli.py
ultrayolo/learningrates.py
ultrayolo/losses.py
ultrayolo/ultrayolo.py
ultrayolo/datasets/__init__.py
ultrayolo/datasets/common.py
ultrayolo/datasets/datasetmode.py
ultrayolo/datasets/datasets.py
ultrayolo/datasets/genanchors.py
ultrayolo/helpers/__init__.py
ultrayolo/helpers/callbacks.py
ultrayolo/helpers/darknet.py
ultrayolo/helpers/draw.py
ultrayolo/layers/__init__.py
ultrayolo/layers/core.py
ultrayolo-0.7.0.dist-info/AUTHORS.rst
ultrayolo-0.7.0.dist-info/LICENSE
ultrayolo-0.7.0.dist-info/METADATA
ultrayolo-0.7.0.dist-info/WHEEL
ultrayolo-0.7.0.dist-info/entry_points.txt
ultrayolo-0.7.0.dist-info/top_level.txt
ultrayolo-0.7.0.dist-info/RECORD
