Metadata-Version: 2.1
Name: ultrayolo
Version: 0.7.0
Summary: tensorflow 2 implemetation of yolo 3 with backbone extensions
Home-page: https://github.com/fabiofumarola/ultrayolo
Author: Fabio Fumarola
Author-email: fabiofumarola@gmail.com
License: Apache Software License 2.0
Keywords: ultrayolo
Platform: UNKNOWN
Classifier: Development Status :: 4 - Beta
Classifier: Intended Audience :: Developers
Classifier: License :: OSI Approved :: Apache Software License
Classifier: Natural Language :: English
Classifier: Programming Language :: Python :: 3
Classifier: Programming Language :: Python :: 3.6
Classifier: Programming Language :: Python :: 3.7
Requires-Python: >=3
Requires-Dist: tensorflow (==2.1.0)
Requires-Dist: tensorflow-addons (==0.7.0)
Requires-Dist: imageio (==2.6.1)
Requires-Dist: imgaug (==0.4.0)
Requires-Dist: pandas
Requires-Dist: numpy (==1.17)
Requires-Dist: pyyaml (==5.3)
Requires-Dist: hydra-core
Requires-Dist: omegaconf
